arus_stream_metawear/__init__.py
arus_stream_metawear/corrector.py
arus_stream_metawear/stream.py
examples/use_metawear_stream.py
arus_stream_metawear-1.0.4.dist-info/WHEEL
arus_stream_metawear-1.0.4.dist-info/METADATA
arus_stream_metawear-1.0.4.dist-info/RECORD
