Metadata-Version: 2.1
Name: arus-stream-metawear
Version: 1.0.4
Summary: arus plugin that helps creating stream for metawear devices
Home-page: https://github.com/qutang/arus-stream-metawear
License: MIT
Keywords: ubiquitous computing,sensing,data processing,bluetooth,internet of things
Author: qutang
Author-email: tqshelly@gmail.com
Requires-Python: >=3.6,<4.0
Classifier: License :: OSI Approved :: MIT License
Classifier: Programming Language :: Python :: 3
Classifier: Programming Language :: Python :: 3.6
Classifier: Programming Language :: Python :: 3.7
Classifier: Topic :: Scientific/Engineering :: Human Machine Interfaces
Classifier: Topic :: Software Development :: Libraries :: Python Modules
Requires-Dist: arus (>=0.4.0,<0.5.0)
Requires-Dist: pymetawear (>=0.12.0,<0.13.0)
Project-URL: Documentation, https://qutang.github.io/arus-stream-metawear/
Project-URL: Repository, https://github.com/qutang/arus-stream-metawear
